chgen/__init__.py
chgen/analysis.py
chgen/functions.py
chgen/wrapper.py
chgen-0.0.1.dist-info/LICENSE
chgen-0.0.1.dist-info/METADATA
chgen-0.0.1.dist-info/WHEEL
chgen-0.0.1.dist-info/top_level.txt
chgen-0.0.1.dist-info/RECORD
