Metadata-Version: 2.1
Name: chgen
Version: 0.0.1
Summary: Comparison of populations using convex hull analysis
Author-email: Kateryna Nikulina <kateryna.nikulina@gmail.com>, Konstantin Sharafutdinov <konstantin.sharafutdinov@phystech.edu>
License: Copyright (c) 2018 The Python Packaging Authority        
Project-URL: Homepage, https://git.rwth-aachen.de/jrc-combine/chgen/
Classifier: Programming Language :: Python :: 3
Classifier: License :: OSI Approved :: MIT License
Classifier: Operating System :: OS Independent
Requires-Python: >=3.7
License-File: LICENSE
